phyddle/__init__.py
phyddle/__main__.py
phyddle/command_line.py
phyddle/estimate.py
phyddle/format.py
phyddle/network.py
phyddle/plot.py
phyddle/simulate.py
phyddle/train.py
phyddle/utilities.py
phyddle-0.3.0.dist-info/METADATA
phyddle-0.3.0.dist-info/WHEEL
phyddle-0.3.0.dist-info/entry_points.txt
phyddle-0.3.0.dist-info/licenses/LICENSE
phyddle-0.3.0.dist-info/RECORD
