Metadata-Version: 2.4
Name: phyddle
Version: 0.3.0
Summary: Software for phylogenetic model exploration with deep learning
Project-URL: Homepage, https://github.com/mlandis/phyddle
Project-URL: Bug Reports, https://github.com/mlandis/phyddle/issues
Project-URL: Documentation, https://mlandis.github.io/phyddle
Author-email: Michael Landis <michael.landis@wustl.edu>, Ammon Thompson <ammonthompson@gmail.com>
License-File: LICENSE
Classifier: Development Status :: 3 - Alpha
Classifier: Environment :: Console
Classifier: Intended Audience :: Science/Research
Classifier: License :: OSI Approved :: MIT License
Classifier: Natural Language :: English
Classifier: Operating System :: OS Independent
Classifier: Programming Language :: Python :: 3
Classifier: Topic :: Scientific/Engineering :: Artificial Intelligence
Classifier: Topic :: Scientific/Engineering :: Bio-Informatics
Classifier: Topic :: Scientific/Engineering :: Mathematics
Requires-Python: >=3.12
Requires-Dist: dendropy>=4.6.0
Requires-Dist: graphviz>=0.20.0
Requires-Dist: h5py>=3.10.0
Requires-Dist: matplotlib>=3.8.2
Requires-Dist: numpy>=1.26.4
Requires-Dist: pandas>=2.2.0
Requires-Dist: pydot>=2.0.0
Requires-Dist: pypdf>=4.0.0
Requires-Dist: scikit-learn>=1.4.0
Requires-Dist: scipy>=1.14.0
Requires-Dist: torch>=2.2.0
Requires-Dist: torchview>=0.2.6
Requires-Dist: tqdm>=4.66.1
